fasted/__init__.py
fasted/idmemo.py
fasted/py.typed
fasted/selfdependent.py
fasted/typing.py
fasted/utils.py
fasted-0.2404.2.dist-info/LICENSE
fasted-0.2404.2.dist-info/METADATA
fasted-0.2404.2.dist-info/WHEEL
fasted-0.2404.2.dist-info/RECORD
