Metadata-Version: 2.1
Name: fasted
Version: 0.2404.2
Summary: FastAPI dependencies and utilities.
License: MIT
Author: Peter Volf
Author-email: do.volfp@gmail.com
Requires-Python: >=3.10,<4.0
Classifier: License :: OSI Approved :: MIT License
Classifier: Programming Language :: Python :: 3
Classifier: Programming Language :: Python :: 3.10
Classifier: Programming Language :: Python :: 3.11
Classifier: Programming Language :: Python :: 3.12
Requires-Dist: fastapi (>=0.100.0)
